{
  "kind": "collectionType",
  "collectionName": "concerts",
  "info": {
    "name": "concert",
    "description": ""
  },
  "options": {
    "increments": true,
    "timestamps": true,
    "draftAndPublish": true
  },
  "pluginOptions": {},
  "attributes": {
    "date": {
      "type": "datetime"
    },
    "venue": {
      "type": "string"
    },
    "tourname": {
      "type": "string"
    },
    "address": {
      "type": "component",
      "repeatable": false,
      "component": "contactinformation.address"
    }
  }
}
